fpex0/CP.py
fpex0/InitialDistribution.py
fpex0/__init__.py
fpex0/baseline.py
fpex0/fokker_planck.py
fpex0/fpex0.py
fpex0/linreg.py
fpex0/setup.py
fpex0/example/ID407-rate_0.60.json
fpex0/example/ID407-rate_1.25.json
fpex0/example/ID407-rate_10.00.json
fpex0/example/ID407-rate_2.50.json
fpex0/example/ID407-rate_20.00.json
fpex0/example/ID407-rate_5.00.json
fpex0/example/__init__.py
fpex0/example/exampleFit.py
fpex0/example/exampleSetup.py
fpex0-0.9.1.dist-info/LICENSE.txt
fpex0-0.9.1.dist-info/METADATA
fpex0-0.9.1.dist-info/WHEEL
fpex0-0.9.1.dist-info/top_level.txt
fpex0-0.9.1.dist-info/RECORD
