Metadata-Version: 2.1
Name: fpex0
Version: 0.9.1
Summary: This package is an implementation of the FPEX0 algorithm, a data-driven de-smearing method for DSC signals.
Author-email: Michael Strik <michael.strik@stud.uni-heidelberg.de>
Maintainer-email: Andreas Sommer <code@andreas-sommer.eu>
License: MIT License
Classifier: Development Status :: 3 - Alpha
Classifier: License :: OSI Approved :: MIT License
Classifier: Programming Language :: Python :: 3
Requires-Python: >=3.7
License-File: LICENSE.txt
Requires-Dist: scipy
Requires-Dist: numpy
Requires-Dist: sympy
